[
  {
    "id": 1,
    "type": "box",
    "x": 50,
    "y": 50,
    "width": 150,
    "height": 60,
    "text": "Control Room",
    "bgColor": "#ffffff",
    "textColor": "#000000",
    "fontSize": 14,
    "shadow": true,
    "dashed": false
  },
  {
    "id": 2,
    "type": "box",
    "x": 50,
    "y": 150,
    "width": 400,
    "height": 550,
    "text": "#1",
    "bgColor": "#e0e0e0",
    "textColor": "#000000",
    "fontSize": 16,
    "shadow": true,
    "dashed": false
  },
  {
    "id": 100,
    "type": "box",
    "x": 80,
    "y": 200,
    "width": 94,
    "height": 30,
    "text": "U1",
    "bgColor": "#ffffff",
    "textColor": "#000000",
    "fontSize": 12,
    "shadow": true,
    "dashed": false
  },
  {
    "id": 101,
    "type": "box",
    "x": 80,
    "y": 235,
    "width": 94,
    "height": 30,
    "text": "U2",
    "bgColor": "#ffffff",
    "textColor": "#000000",
    "fontSize": 12,
    "shadow": true,
    "dashed": false
  },
  {
    "id": 102,
    "type": "box",
    "x": 80,
    "y": 270,
    "width": 94,
    "height": 30,
    "text": "U3",
    "bgColor": "#ffffff",
    "textColor": "#000000",
    "fontSize": 12,
    "shadow": true,
    "dashed": false
  },
  {
    "id": 103,
    "type": "box",
    "x": 80,
    "y": 305,
    "width": 94,
    "height": 30,
    "text": "U4",
    "bgColor": "#ffffff",
    "textColor": "#000000",
    "fontSize": 12,
    "shadow": true,
    "dashed": false
  },
  {
    "id": 104,
    "type": "box",
    "x": 80,
    "y": 340,
    "width": 94,
    "height": 30,
    "text": "U5",
    "bgColor": "#ffffff",
    "textColor": "#000000",
    "fontSize": 12,
    "shadow": true,
    "dashed": false
  },
  {
    "id": 105,
    "type": "box",
    "x": 80,
    "y": 375,
    "width": 94,
    "height": 30,
    "text": "U6",
    "bgColor": "#ffffff",
    "textColor": "#000000",
    "fontSize": 12,
    "shadow": true,
    "dashed": false
  },
  {
    "id": 106,
    "type": "box",
    "x": 80,
    "y": 410,
    "width": 94,
    "height": 30,
    "text": "U7",
    "bgColor": "#ffffff",
    "textColor": "#000000",
    "fontSize": 12,
    "shadow": true,
    "dashed": false
  },
  {
    "id": 107,
    "type": "box",
    "x": 80,
    "y": 445,
    "width": 94,
    "height": 30,
    "text": "U8",
    "bgColor": "#ffffff",
    "textColor": "#000000",
    "fontSize": 12,
    "shadow": true,
    "dashed": false
  },
  {
    "id": 108,
    "type": "box",
    "x": 80,
    "y": 480,
    "width": 94,
    "height": 30,
    "text": "U9",
    "bgColor": "#ffffff",
    "textColor": "#000000",
    "fontSize": 12,
    "shadow": true,
    "dashed": false
  },
  {
    "id": 109,
    "type": "box",
    "x": 80,
    "y": 515,
    "width": 94,
    "height": 30,
    "text": "U10",
    "bgColor": "#ffffff",
    "textColor": "#000000",
    "fontSize": 12,
    "shadow": true,
    "dashed": false
  },
  {
    "id": 200,
    "type": "line",
    "x1": 125,
    "y1": 110,
    "x2": 127,
    "y2": 200,
    "label": "",
    "startCircle": false,
    "endCircle": false,
    "arrow": true,
    "strokeWidth": 2
  },
  {
    "id": 201,
    "type": "line",
    "x1": 125,
    "y1": 110,
    "x2": 127,
    "y2": 235,
    "label": "",
    "startCircle": false,
    "endCircle": false,
    "arrow": true,
    "strokeWidth": 2
  },
  {
    "id": 202,
    "type": "line",
    "x1": 125,
    "y1": 110,
    "x2": 127,
    "y2": 270,
    "label": "",
    "startCircle": false,
    "endCircle": false,
    "arrow": true,
    "strokeWidth": 2
  },
  {
    "id": 203,
    "type": "line",
    "x1": 125,
    "y1": 110,
    "x2": 127,
    "y2": 305,
    "label": "",
    "startCircle": false,
    "endCircle": false,
    "arrow": true,
    "strokeWidth": 2
  },
  {
    "id": 204,
    "type": "line",
    "x1": 125,
    "y1": 110,
    "x2": 127,
    "y2": 340,
    "label": "",
    "startCircle": false,
    "endCircle": false,
    "arrow": true,
    "strokeWidth": 2
  },
  {
    "id": 205,
    "type": "line",
    "x1": 125,
    "y1": 110,
    "x2": 127,
    "y2": 375,
    "label": "",
    "startCircle": false,
    "endCircle": false,
    "arrow": true,
    "strokeWidth": 2
  },
  {
    "id": 206,
    "type": "line",
    "x1": 125,
    "y1": 110,
    "x2": 127,
    "y2": 410,
    "label": "",
    "startCircle": false,
    "endCircle": false,
    "arrow": true,
    "strokeWidth": 2
  },
  {
    "id": 207,
    "type": "line",
    "x1": 125,
    "y1": 110,
    "x2": 127,
    "y2": 445,
    "label": "",
    "startCircle": false,
    "endCircle": false,
    "arrow": true,
    "strokeWidth": 2
  },
  {
    "id": 208,
    "type": "line",
    "x1": 125,
    "y1": 110,
    "x2": 127,
    "y2": 480,
    "label": "",
    "startCircle": false,
    "endCircle": false,
    "arrow": true,
    "strokeWidth": 2
  },
  {
    "id": 209,
    "type": "line",
    "x1": 125,
    "y1": 110,
    "x2": 127,
    "y2": 515,
    "label": "",
    "startCircle": false,
    "endCircle": false,
    "arrow": true,
    "strokeWidth": 2
  },
  {
    "id": 3,
    "type": "box",
    "x": 480,
    "y": 150,
    "width": 950,
    "height": 250,
    "text": "#2 - U1 Detail",
    "bgColor": "#e0f0e0",
    "textColor": "#000000",
    "fontSize": 16,
    "shadow": true,
    "dashed": false
  },
  {
    "id": 300,
    "type": "line",
    "x1": 520,
    "y1": 230,
    "x2": 1390,
    "y2": 230,
    "label": "Power Bus",
    "startCircle": false,
    "endCircle": false,
    "arrow": false,
    "strokeWidth": 3
  },
  {
    "id": 310,
    "type": "box",
    "x": 530,
    "y": 280,
    "width": 47,
    "height": 34,
    "text": "GB1",
    "bgColor": "#ffffff",
    "textColor": "#000000",
    "fontSize": 11,
    "shadow": true,
    "dashed": false
  },
  {
    "id": 311,
    "type": "box",
    "x": 590,
    "y": 280,
    "width": 47,
    "height": 34,
    "text": "GB2",
    "bgColor": "#ffffff",
    "textColor": "#000000",
    "fontSize": 11,
    "shadow": true,
    "dashed": false
  },
  {
    "id": 312,
    "type": "box",
    "x": 650,
    "y": 280,
    "width": 47,
    "height": 34,
    "text": "GB3",
    "bgColor": "#ffffff",
    "textColor": "#000000",
    "fontSize": 11,
    "shadow": true,
    "dashed": false
  },
  {
    "id": 313,
    "type": "box",
    "x": 710,
    "y": 280,
    "width": 47,
    "height": 34,
    "text": "GB4",
    "bgColor": "#ffffff",
    "textColor": "#000000",
    "fontSize": 11,
    "shadow": true,
    "dashed": false
  },
  {
    "id": 314,
    "type": "box",
    "x": 770,
    "y": 280,
    "width": 47,
    "height": 34,
    "text": "GB5",
    "bgColor": "#ffffff",
    "textColor": "#000000",
    "fontSize": 11,
    "shadow": true,
    "dashed": false
  },
  {
    "id": 315,
    "type": "box",
    "x": 830,
    "y": 280,
    "width": 47,
    "height": 34,
    "text": "GB6",
    "bgColor": "#ffffff",
    "textColor": "#000000",
    "fontSize": 11,
    "shadow": true,
    "dashed": false
  },
  {
    "id": 316,
    "type": "box",
    "x": 890,
    "y": 280,
    "width": 47,
    "height": 34,
    "text": "GB7",
    "bgColor": "#ffffff",
    "textColor": "#000000",
    "fontSize": 11,
    "shadow": true,
    "dashed": false
  },
  {
    "id": 317,
    "type": "box",
    "x": 950,
    "y": 280,
    "width": 47,
    "height": 34,
    "text": "GB8",
    "bgColor": "#ffffff",
    "textColor": "#000000",
    "fontSize": 11,
    "shadow": true,
    "dashed": false
  },
  {
    "id": 318,
    "type": "box",
    "x": 1010,
    "y": 280,
    "width": 47,
    "height": 34,
    "text": "GB9",
    "bgColor": "#ffffff",
    "textColor": "#000000",
    "fontSize": 11,
    "shadow": true,
    "dashed": false
  },
  {
    "id": 319,
    "type": "box",
    "x": 1070,
    "y": 280,
    "width": 47,
    "height": 34,
    "text": "GB10",
    "bgColor": "#ffffff",
    "textColor": "#000000",
    "fontSize": 10,
    "shadow": true,
    "dashed": false
  },
  {
    "id": 320,
    "type": "box",
    "x": 1130,
    "y": 280,
    "width": 47,
    "height": 34,
    "text": "GB11",
    "bgColor": "#ffffff",
    "textColor": "#000000",
    "fontSize": 10,
    "shadow": true,
    "dashed": false
  },
  {
    "id": 321,
    "type": "box",
    "x": 1190,
    "y": 280,
    "width": 47,
    "height": 34,
    "text": "GB12",
    "bgColor": "#ffffff",
    "textColor": "#000000",
    "fontSize": 10,
    "shadow": true,
    "dashed": false
  },
  {
    "id": 322,
    "type": "box",
    "x": 1250,
    "y": 280,
    "width": 47,
    "height": 34,
    "text": "GB13",
    "bgColor": "#ffffff",
    "textColor": "#000000",
    "fontSize": 10,
    "shadow": true,
    "dashed": false
  },
  {
    "id": 323,
    "type": "box",
    "x": 1310,
    "y": 280,
    "width": 47,
    "height": 34,
    "text": "GB14",
    "bgColor": "#ffffff",
    "textColor": "#000000",
    "fontSize": 10,
    "shadow": true,
    "dashed": false
  },
  {
    "id": 324,
    "type": "box",
    "x": 1370,
    "y": 280,
    "width": 47,
    "height": 34,
    "text": "GB15",
    "bgColor": "#ffffff",
    "textColor": "#000000",
    "fontSize": 10,
    "shadow": true,
    "dashed": false
  },
  {
    "id": 400,
    "type": "line",
    "x1": 553,
    "y1": 230,
    "x2": 553,
    "y2": 280,
    "label": "",
    "startCircle": false,
    "endCircle": true,
    "arrow": false,
    "strokeWidth": 2
  },
  {
    "id": 401,
    "type": "line",
    "x1": 613,
    "y1": 230,
    "x2": 613,
    "y2": 280,
    "label": "",
    "startCircle": false,
    "endCircle": true,
    "arrow": false,
    "strokeWidth": 2
  },
  {
    "id": 402,
    "type": "line",
    "x1": 673,
    "y1": 230,
    "x2": 673,
    "y2": 280,
    "label": "",
    "startCircle": false,
    "endCircle": true,
    "arrow": false,
    "strokeWidth": 2
  },
  {
    "id": 403,
    "type": "line",
    "x1": 733,
    "y1": 230,
    "x2": 733,
    "y2": 280,
    "label": "",
    "startCircle": false,
    "endCircle": true,
    "arrow": false,
    "strokeWidth": 2
  },
  {
    "id": 404,
    "type": "line",
    "x1": 793,
    "y1": 230,
    "x2": 793,
    "y2": 280,
    "label": "",
    "startCircle": false,
    "endCircle": true,
    "arrow": false,
    "strokeWidth": 2
  },
  {
    "id": 405,
    "type": "line",
    "x1": 853,
    "y1": 230,
    "x2": 853,
    "y2": 280,
    "label": "",
    "startCircle": false,
    "endCircle": true,
    "arrow": false,
    "strokeWidth": 2
  },
  {
    "id": 406,
    "type": "line",
    "x1": 913,
    "y1": 230,
    "x2": 913,
    "y2": 280,
    "label": "",
    "startCircle": false,
    "endCircle": true,
    "arrow": false,
    "strokeWidth": 2
  },
  {
    "id": 407,
    "type": "line",
    "x1": 973,
    "y1": 230,
    "x2": 973,
    "y2": 280,
    "label": "",
    "startCircle": false,
    "endCircle": true,
    "arrow": false,
    "strokeWidth": 2
  },
  {
    "id": 408,
    "type": "line",
    "x1": 1033,
    "y1": 230,
    "x2": 1033,
    "y2": 280,
    "label": "",
    "startCircle": false,
    "endCircle": true,
    "arrow": false,
    "strokeWidth": 2
  },
  {
    "id": 409,
    "type": "line",
    "x1": 1093,
    "y1": 230,
    "x2": 1093,
    "y2": 280,
    "label": "",
    "startCircle": false,
    "endCircle": true,
    "arrow": false,
    "strokeWidth": 2
  },
  {
    "id": 410,
    "type": "line",
    "x1": 1153,
    "y1": 230,
    "x2": 1153,
    "y2": 280,
    "label": "",
    "startCircle": false,
    "endCircle": true,
    "arrow": false,
    "strokeWidth": 2
  },
  {
    "id": 411,
    "type": "line",
    "x1": 1213,
    "y1": 230,
    "x2": 1213,
    "y2": 280,
    "label": "",
    "startCircle": false,
    "endCircle": true,
    "arrow": false,
    "strokeWidth": 2
  },
  {
    "id": 412,
    "type": "line",
    "x1": 1273,
    "y1": 230,
    "x2": 1273,
    "y2": 280,
    "label": "",
    "startCircle": false,
    "endCircle": true,
    "arrow": false,
    "strokeWidth": 2
  },
  {
    "id": 413,
    "type": "line",
    "x1": 1333,
    "y1": 230,
    "x2": 1333,
    "y2": 280,
    "label": "",
    "startCircle": false,
    "endCircle": true,
    "arrow": false,
    "strokeWidth": 2
  },
  {
    "id": 414,
    "type": "line",
    "x1": 1393,
    "y1": 230,
    "x2": 1393,
    "y2": 280,
    "label": "",
    "startCircle": false,
    "endCircle": true,
    "arrow": false,
    "strokeWidth": 2
  },
  {
    "id": 500,
    "type": "line",
    "x1": 577,
    "y1": 297,
    "x2": 590,
    "y2": 297,
    "label": "",
    "startCircle": false,
    "endCircle": false,
    "arrow": true,
    "strokeWidth": 2
  },
  {
    "id": 501,
    "type": "line",
    "x1": 637,
    "y1": 297,
    "x2": 650,
    "y2": 297,
    "label": "",
    "startCircle": false,
    "endCircle": false,
    "arrow": true,
    "strokeWidth": 2
  },
  {
    "id": 502,
    "type": "line",
    "x1": 697,
    "y1": 297,
    "x2": 710,
    "y2": 297,
    "label": "",
    "startCircle": false,
    "endCircle": false,
    "arrow": true,
    "strokeWidth": 2
  },
  {
    "id": 503,
    "type": "line",
    "x1": 757,
    "y1": 297,
    "x2": 770,
    "y2": 297,
    "label": "",
    "startCircle": false,
    "endCircle": false,
    "arrow": true,
    "strokeWidth": 2
  },
  {
    "id": 504,
    "type": "line",
    "x1": 817,
    "y1": 297,
    "x2": 830,
    "y2": 297,
    "label": "",
    "startCircle": false,
    "endCircle": false,
    "arrow": true,
    "strokeWidth": 2
  },
  {
    "id": 505,
    "type": "line",
    "x1": 877,
    "y1": 297,
    "x2": 890,
    "y2": 297,
    "label": "",
    "startCircle": false,
    "endCircle": false,
    "arrow": true,
    "strokeWidth": 2
  },
  {
    "id": 506,
    "type": "line",
    "x1": 937,
    "y1": 297,
    "x2": 950,
    "y2": 297,
    "label": "",
    "startCircle": false,
    "endCircle": false,
    "arrow": true,
    "strokeWidth": 2
  },
  {
    "id": 507,
    "type": "line",
    "x1": 997,
    "y1": 297,
    "x2": 1010,
    "y2": 297,
    "label": "",
    "startCircle": false,
    "endCircle": false,
    "arrow": true,
    "strokeWidth": 2
  },
  {
    "id": 508,
    "type": "line",
    "x1": 1057,
    "y1": 297,
    "x2": 1070,
    "y2": 297,
    "label": "",
    "startCircle": false,
    "endCircle": false,
    "arrow": true,
    "strokeWidth": 2
  },
  {
    "id": 509,
    "type": "line",
    "x1": 1117,
    "y1": 297,
    "x2": 1130,
    "y2": 297,
    "label": "",
    "startCircle": false,
    "endCircle": false,
    "arrow": true,
    "strokeWidth": 2
  },
  {
    "id": 510,
    "type": "line",
    "x1": 1177,
    "y1": 297,
    "x2": 1190,
    "y2": 297,
    "label": "",
    "startCircle": false,
    "endCircle": false,
    "arrow": true,
    "strokeWidth": 2
  },
  {
    "id": 511,
    "type": "line",
    "x1": 1237,
    "y1": 297,
    "x2": 1250,
    "y2": 297,
    "label": "",
    "startCircle": false,
    "endCircle": false,
    "arrow": true,
    "strokeWidth": 2
  },
  {
    "id": 512,
    "type": "line",
    "x1": 1297,
    "y1": 297,
    "x2": 1310,
    "y2": 297,
    "label": "",
    "startCircle": false,
    "endCircle": false,
    "arrow": true,
    "strokeWidth": 2
  },
  {
    "id": 513,
    "type": "line",
    "x1": 1357,
    "y1": 297,
    "x2": 1370,
    "y2": 297,
    "label": "",
    "startCircle": false,
    "endCircle": false,
    "arrow": true,
    "strokeWidth": 2
  },
  {
    "id": 4,
    "type": "box",
    "x": 480,
    "y": 430,
    "width": 950,
    "height": 270,
    "text": "#3 - Dimmer Detail",
    "bgColor": "#f0e0e0",
    "textColor": "#000000",
    "fontSize": 16,
    "shadow": true,
    "dashed": false
  },
  {
    "id": 600,
    "type": "box",
    "x": 520,
    "y": 480,
    "width": 136,
    "height": 34,
    "text": "Dimmer",
    "bgColor": "#ffffff",
    "textColor": "#000000",
    "fontSize": 12,
    "shadow": true,
    "dashed": false
  },
  {
    "id": 601,
    "type": "box",
    "x": 690,
    "y": 480,
    "width": 136,
    "height": 34,
    "text": "Dimmer",
    "bgColor": "#ffffff",
    "textColor": "#000000",
    "fontSize": 12,
    "shadow": true,
    "dashed": false
  },
  {
    "id": 602,
    "type": "box",
    "x": 860,
    "y": 480,
    "width": 136,
    "height": 34,
    "text": "Dimmer",
    "bgColor": "#ffffff",
    "textColor": "#000000",
    "fontSize": 12,
    "shadow": true,
    "dashed": false
  },
  {
    "id": 603,
    "type": "box",
    "x": 1030,
    "y": 480,
    "width": 136,
    "height": 34,
    "text": "Dimmer",
    "bgColor": "#ffffff",
    "textColor": "#000000",
    "fontSize": 12,
    "shadow": true,
    "dashed": false
  },
  {
    "id": 604,
    "type": "box",
    "x": 1200,
    "y": 480,
    "width": 136,
    "height": 34,
    "text": "Dimmer",
    "bgColor": "#ffffff",
    "textColor": "#000000",
    "fontSize": 12,
    "shadow": true,
    "dashed": false
  },
  {
    "id": 700,
    "type": "circle",
    "x": 524,
    "y": 555,
    "radius": 17,
    "text": "",
    "bgColor": "#ffffff",
    "textColor": "#000000",
    "fontSize": 12,
    "shadow": true,
    "dashed": false
  },
  {
    "id": 701,
    "type": "circle",
    "x": 558,
    "y": 555,
    "radius": 17,
    "text": "",
    "bgColor": "#ffffff",
    "textColor": "#000000",
    "fontSize": 12,
    "shadow": true,
    "dashed": false
  },
  {
    "id": 702,
    "type": "circle",
    "x": 592,
    "y": 555,
    "radius": 17,
    "text": "",
    "bgColor": "#ffffff",
    "textColor": "#000000",
    "fontSize": 12,
    "shadow": true,
    "dashed": false
  },
  {
    "id": 703,
    "type": "circle",
    "x": 626,
    "y": 555,
    "radius": 17,
    "text": "",
    "bgColor": "#ffffff",
    "textColor": "#000000",
    "fontSize": 12,
    "shadow": true,
    "dashed": false
  },
  {
    "id": 800,
    "type": "line",
    "x1": 541,
    "y1": 514,
    "x2": 541,
    "y2": 555,
    "label": "",
    "startCircle": false,
    "endCircle": true,
    "arrow": false,
    "strokeWidth": 2
  },
  {
    "id": 801,
    "type": "line",
    "x1": 575,
    "y1": 514,
    "x2": 575,
    "y2": 555,
    "label": "",
    "startCircle": false,
    "endCircle": true,
    "arrow": false,
    "strokeWidth": 2
  },
  {
    "id": 802,
    "type": "line",
    "x1": 609,
    "y1": 514,
    "x2": 609,
    "y2": 555,
    "label": "",
    "startCircle": false,
    "endCircle": true,
    "arrow": false,
    "strokeWidth": 2
  },
  {
    "id": 803,
    "type": "line",
    "x1": 643,
    "y1": 514,
    "x2": 643,
    "y2": 555,
    "label": "",
    "startCircle": false,
    "endCircle": true,
    "arrow": false,
    "strokeWidth": 2
  },
  {
    "id": 704,
    "type": "circle",
    "x": 694,
    "y": 555,
    "radius": 17,
    "text": "",
    "bgColor": "#ffffff",
    "textColor": "#000000",
    "fontSize": 12,
    "shadow": true,
    "dashed": false
  },
  {
    "id": 705,
    "type": "circle",
    "x": 728,
    "y": 555,
    "radius": 17,
    "text": "",
    "bgColor": "#ffffff",
    "textColor": "#000000",
    "fontSize": 12,
    "shadow": true,
    "dashed": false
  },
  {
    "id": 706,
    "type": "circle",
    "x": 762,
    "y": 555,
    "radius": 17,
    "text": "",
    "bgColor": "#ffffff",
    "textColor": "#000000",
    "fontSize": 12,
    "shadow": true,
    "dashed": false
  },
  {
    "id": 707,
    "type": "circle",
    "x": 796,
    "y": 555,
    "radius": 17,
    "text": "",
    "bgColor": "#ffffff",
    "textColor": "#000000",
    "fontSize": 12,
    "shadow": true,
    "dashed": false
  },
  {
    "id": 804,
    "type": "line",
    "x1": 711,
    "y1": 514,
    "x2": 711,
    "y2": 555,
    "label": "",
    "startCircle": false,
    "endCircle": true,
    "arrow": false,
    "strokeWidth": 2
  },
  {
    "id": 805,
    "type": "line",
    "x1": 745,
    "y1": 514,
    "x2": 745,
    "y2": 555,
    "label": "",
    "startCircle": false,
    "endCircle": true,
    "arrow": false,
    "strokeWidth": 2
  },
  {
    "id": 806,
    "type": "line",
    "x1": 779,
    "y1": 514,
    "x2": 779,
    "y2": 555,
    "label": "",
    "startCircle": false,
    "endCircle": true,
    "arrow": false,
    "strokeWidth": 2
  },
  {
    "id": 807,
    "type": "line",
    "x1": 813,
    "y1": 514,
    "x2": 813,
    "y2": 555,
    "label": "",
    "startCircle": false,
    "endCircle": true,
    "arrow": false,
    "strokeWidth": 2
  },
  {
    "id": 708,
    "type": "circle",
    "x": 864,
    "y": 555,
    "radius": 17,
    "text": "",
    "bgColor": "#ffffff",
    "textColor": "#000000",
    "fontSize": 12,
    "shadow": true,
    "dashed": false
  },
  {
    "id": 709,
    "type": "circle",
    "x": 898,
    "y": 555,
    "radius": 17,
    "text": "",
    "bgColor": "#ffffff",
    "textColor": "#000000",
    "fontSize": 12,
    "shadow": true,
    "dashed": false
  },
  {
    "id": 710,
    "type": "circle",
    "x": 932,
    "y": 555,
    "radius": 17,
    "text": "",
    "bgColor": "#ffffff",
    "textColor": "#000000",
    "fontSize": 12,
    "shadow": true,
    "dashed": false
  },
  {
    "id": 711,
    "type": "circle",
    "x": 966,
    "y": 555,
    "radius": 17,
    "text": "",
    "bgColor": "#ffffff",
    "textColor": "#000000",
    "fontSize": 12,
    "shadow": true,
    "dashed": false
  },
  {
    "id": 808,
    "type": "line",
    "x1": 881,
    "y1": 514,
    "x2": 881,
    "y2": 555,
    "label": "",
    "startCircle": false,
    "endCircle": true,
    "arrow": false,
    "strokeWidth": 2
  },
  {
    "id": 809,
    "type": "line",
    "x1": 915,
    "y1": 514,
    "x2": 915,
    "y2": 555,
    "label": "",
    "startCircle": false,
    "endCircle": true,
    "arrow": false,
    "strokeWidth": 2
  },
  {
    "id": 810,
    "type": "line",
    "x1": 949,
    "y1": 514,
    "x2": 949,
    "y2": 555,
    "label": "",
    "startCircle": false,
    "endCircle": true,
    "arrow": false,
    "strokeWidth": 2
  },
  {
    "id": 811,
    "type": "line",
    "x1": 983,
    "y1": 514,
    "x2": 983,
    "y2": 555,
    "label": "",
    "startCircle": false,
    "endCircle": true,
    "arrow": false,
    "strokeWidth": 2
  },
  {
    "id": 712,
    "type": "circle",
    "x": 1034,
    "y": 555,
    "radius": 17,
    "text": "",
    "bgColor": "#ffffff",
    "textColor": "#000000",
    "fontSize": 12,
    "shadow": true,
    "dashed": false
  },
  {
    "id": 713,
    "type": "circle",
    "x": 1068,
    "y": 555,
    "radius": 17,
    "text": "",
    "bgColor": "#ffffff",
    "textColor": "#000000",
    "fontSize": 12,
    "shadow": true,
    "dashed": false
  },
  {
    "id": 714,
    "type": "circle",
    "x": 1102,
    "y": 555,
    "radius": 17,
    "text": "",
    "bgColor": "#ffffff",
    "textColor": "#000000",
    "fontSize": 12,
    "shadow": true,
    "dashed": false
  },
  {
    "id": 715,
    "type": "circle",
    "x": 1136,
    "y": 555,
    "radius": 17,
    "text": "",
    "bgColor": "#ffffff",
    "textColor": "#000000",
    "fontSize": 12,
    "shadow": true,
    "dashed": false
  },
  {
    "id": 812,
    "type": "line",
    "x1": 1051,
    "y1": 514,
    "x2": 1051,
    "y2": 555,
    "label": "",
    "startCircle": false,
    "endCircle": true,
    "arrow": false,
    "strokeWidth": 2
  },
  {
    "id": 813,
    "type": "line",
    "x1": 1085,
    "y1": 514,
    "x2": 1085,
    "y2": 555,
    "label": "",
    "startCircle": false,
    "endCircle": true,
    "arrow": false,
    "strokeWidth": 2
  },
  {
    "id": 814,
    "type": "line",
    "x1": 1119,
    "y1": 514,
    "x2": 1119,
    "y2": 555,
    "label": "",
    "startCircle": false,
    "endCircle": true,
    "arrow": false,
    "strokeWidth": 2
  },
  {
    "id": 815,
    "type": "line",
    "x1": 1153,
    "y1": 514,
    "x2": 1153,
    "y2": 555,
    "label": "",
    "startCircle": false,
    "endCircle": true,
    "arrow": false,
    "strokeWidth": 2
  },
  {
    "id": 716,
    "type": "circle",
    "x": 1204,
    "y": 555,
    "radius": 17,
    "text": "",
    "bgColor": "#ffffff",
    "textColor": "#000000",
    "fontSize": 12,
    "shadow": true,
    "dashed": false
  },
  {
    "id": 717,
    "type": "circle",
    "x": 1238,
    "y": 555,
    "radius": 17,
    "text": "",
    "bgColor": "#ffffff",
    "textColor": "#000000",
    "fontSize": 12,
    "shadow": true,
    "dashed": false
  },
  {
    "id": 718,
    "type": "circle",
    "x": 1272,
    "y": 555,
    "radius": 17,
    "text": "",
    "bgColor": "#ffffff",
    "textColor": "#000000",
    "fontSize": 12,
    "shadow": true,
    "dashed": false
  },
  {
    "id": 719,
    "type": "circle",
    "x": 1306,
    "y": 555,
    "radius": 17,
    "text": "",
    "bgColor": "#ffffff",
    "textColor": "#000000",
    "fontSize": 12,
    "shadow": true,
    "dashed": false
  },
  {
    "id": 816,
    "type": "line",
    "x1": 1221,
    "y1": 514,
    "x2": 1221,
    "y2": 555,
    "label": "",
    "startCircle": false,
    "endCircle": true,
    "arrow": false,
    "strokeWidth": 2
  },
  {
    "id": 817,
    "type": "line",
    "x1": 1255,
    "y1": 514,
    "x2": 1255,
    "y2": 555,
    "label": "",
    "startCircle": false,
    "endCircle": true,
    "arrow": false,
    "strokeWidth": 2
  },
  {
    "id": 818,
    "type": "line",
    "x1": 1289,
    "y1": 514,
    "x2": 1289,
    "y2": 555,
    "label": "",
    "startCircle": false,
    "endCircle": true,
    "arrow": false,
    "strokeWidth": 2
  },
  {
    "id": 819,
    "type": "line",
    "x1": 1323,
    "y1": 514,
    "x2": 1323,
    "y2": 555,
    "label": "",
    "startCircle": false,
    "endCircle": true,
    "arrow": false,
    "strokeWidth": 2
  }
]
